xxiop/__init__.py
xxiop/op.py
xxiop-1.1.2.dist-info/licenses/LICENSE
xxiop-1.1.2.dist-info/METADATA
xxiop-1.1.2.dist-info/WHEEL
xxiop-1.1.2.dist-info/top_level.txt
xxiop-1.1.2.dist-info/RECORD
