Metadata-Version: 2.4
Name: xxiop
Version: 1.1.2
Summary: Python package for cosmological power spectrum, 21cm signal, and optical depth calculations.
Author-email: Hajime Hinata <onmyojiflow@gmail.com>
License-Expression: MIT
Project-URL: Homepage, https://github.com/SOYONAOC/xxiop
Project-URL: Repository, https://github.com/SOYONAOC/xxiop
Project-URL: Bug Reports, https://github.com/SOYONAOC/xxiop/issues
Project-URL: Documentation, https://github.com/SOYONAOC/xxiop#readme
Keywords: cosmology,power spectrum,21cm,optical depth,astrophysics
Classifier: Development Status :: 3 - Alpha
Classifier: Intended Audience :: Science/Research
Classifier: Operating System :: OS Independent
Classifier: Programming Language :: Python :: 3
Classifier: Programming Language :: Python :: 3.7
Classifier: Programming Language :: Python :: 3.8
Classifier: Programming Language :: Python :: 3.9
Classifier: Programming Language :: Python :: 3.10
Classifier: Programming Language :: Python :: 3.11
Classifier: Programming Language :: Python :: 3.12
Classifier: Topic :: Scientific/Engineering :: Astronomy
Classifier: Topic :: Scientific/Engineering :: Physics
Requires-Python: >=3.7
License-File: LICENSE
Requires-Dist: numpy>=1.18.0
Requires-Dist: scipy>=1.5.0
Requires-Dist: astropy>=4.0
Requires-Dist: matplotlib>=3.0.0
Requires-Dist: pandas>=1.0.0
Requires-Dist: joblib>=1.0.0
Requires-Dist: filelock>=3.0.0
Requires-Dist: massfunc
Provides-Extra: dev
Requires-Dist: pytest>=6.0; extra == "dev"
Requires-Dist: pytest-cov>=2.0; extra == "dev"
Requires-Dist: black>=21.0; extra == "dev"
Requires-Dist: flake8>=3.8; extra == "dev"
Requires-Dist: mypy>=0.800; extra == "dev"
Requires-Dist: pre-commit>=2.15.0; extra == "dev"
Provides-Extra: docs
Requires-Dist: sphinx>=4.0; extra == "docs"
Requires-Dist: sphinx-rtd-theme>=1.0; extra == "docs"
Requires-Dist: numpydoc>=1.1; extra == "docs"
Requires-Dist: sphinx-autoapi>=2.0; extra == "docs"
Provides-Extra: test
Requires-Dist: pytest>=6.0; extra == "test"
Requires-Dist: pytest-cov>=2.0; extra == "test"
Requires-Dist: pytest-xdist>=2.0; extra == "test"
Dynamic: license-file
